montytestpackage/__init__.py
montytestpackage/montytestpackage.py
montytestpackage-0.0.1.dist-info/METADATA
montytestpackage-0.0.1.dist-info/WHEEL
montytestpackage-0.0.1.dist-info/top_level.txt
montytestpackage-0.0.1.dist-info/RECORD
